core/__init__.py
core/__main__.py
core/adapters.py
core/constants.py
core/exceptions.py
core/generator.py
core/logger.py
core/models.py
core/prompt.py
core/runner.py
core/templates.py
core/utils.py
core/cli/args_parser.py
core/cli/cli.py
core/cli/commands.py
core/config/config.py
core/config/files.py
core/config/paths.py
gitk-0.1.3.dist-info/licenses/LICENSE
gitk-0.1.3.dist-info/METADATA
gitk-0.1.3.dist-info/WHEEL
gitk-0.1.3.dist-info/entry_points.txt
gitk-0.1.3.dist-info/top_level.txt
gitk-0.1.3.dist-info/RECORD
