Metadata-Version: 2.4
Name: gitk
Version: 0.1.3
Summary: AI-powered CLI tool for generating git commit messages
Author-email: xifOO <wedyi28111@gmail.com>
License: MIT
Keywords: git,commit,ai,cli
Classifier: Programming Language :: Python :: 3.11
Classifier: Programming Language :: Python :: 3.12
Classifier: License :: OSI Approved :: MIT License
Classifier: Operating System :: OS Independent
Classifier: Topic :: Software Development :: Version Control
Classifier: Environment :: Console
Requires-Python: >=3.11
License-File: LICENSE
Requires-Dist: click<9.0.0,>=8.0.0
Requires-Dist: questionary<2.0.0,>=1.10.0
Requires-Dist: requests<3.0.0,>=2.25.0
Requires-Dist: PyYAML<7.0,>=6.0
Requires-Dist: pydantic<3.0.0,>=1.10.0
Provides-Extra: dev
Requires-Dist: black<24.0,>=23.0; extra == "dev"
Requires-Dist: ruff<0.13.0,>=0.1.0; extra == "dev"
Requires-Dist: mypy<2.0,>=1.0; extra == "dev"
Requires-Dist: pytest<8.0,>=7.0; extra == "dev"
Dynamic: license-file
